zenmpx/__about__.py
zenmpx/__init__.py
zenmpx/scheduling.py
zenmpx-0.0.1.dist-info/METADATA
zenmpx-0.0.1.dist-info/WHEEL
zenmpx-0.0.1.dist-info/RECORD
