Metadata-Version: 2.4
Name: zenmpx
Version: 0.0.1
Project-URL: Documentation, https://github.com/bernard jiang/zenmpx#readme
Project-URL: Issues, https://github.com/bernard jiang/zenmpx/issues
Project-URL: Source, https://github.com/bernard jiang/zenmpx
Author-email: bernard jiang <bernardjiang5@outlook.com>
License-Expression: MIT
Classifier: Development Status :: 4 - Beta
Classifier: Programming Language :: Python
Classifier: Programming Language :: Python :: 3.8
Classifier: Programming Language :: Python :: 3.9
Classifier: Programming Language :: Python :: 3.10
Classifier: Programming Language :: Python :: 3.11
Classifier: Programming Language :: Python :: 3.12
Classifier: Programming Language :: Python :: Implementation :: CPython
Classifier: Programming Language :: Python :: Implementation :: PyPy
Requires-Python: >=3.8
